README
setup.py
easy_graph/__init__.py
easy_graph/easy_graph.py
easy_graph.egg-info/PKG-INFO
easy_graph.egg-info/SOURCES.txt
easy_graph.egg-info/dependency_links.txt
easy_graph.egg-info/entry_points.txt
easy_graph.egg-info/top_level.txt
easy_graph.egg-info/zip-safe