Metadata-Version: 1.0
Name: easy-graph
Version: 0.1
Summary: Easily turn your python data into a flot graph in a static html file.
Home-page: https://github.com/JesseAldridge/easy_graph
Author: Jesse Aldridge
Author-email: JesseAldridge@gmail.com
License: MIT
Keywords: graph graphing plot
Platform: UNKNOWN
